algebra2x/__init__.py
algebra2x/algebra.py
algebra2x/function.py
algebra2x/pretty.py
algebra2x/util.py
algebra2x/ops/__init__.py
algebra2x/ops/add.py
algebra2x/ops/diff.py
algebra2x/ops/mul.py
algebra2x/ops/reverse.py
algebra2x/ops/select.py
algebra2x/ops/shift.py
algebra2x/ops/stretch.py
algebra2x/ops/tensor.py
algebra2x/ops/transform.py
Algebra2x-0.1.dist-info/LICENCE.txt
Algebra2x-0.1.dist-info/METADATA
Algebra2x-0.1.dist-info/WHEEL
Algebra2x-0.1.dist-info/top_level.txt
Algebra2x-0.1.dist-info/RECORD
