Metadata-Version: 2.1
Name: Algebra2x
Version: 0.1
Summary: basic pip package
Author: alen manson
Requires-Python: >=3.1
License-File: LICENCE.txt
Requires-Dist: numpy >=1.16
Requires-Dist: plum-dispatch >=1
Requires-Dist: backends >=1
